dictionary/__init__.py
dictionary/dictionary.py
dictionary_from_api-2.1.0.dist-info/METADATA
dictionary_from_api-2.1.0.dist-info/WHEEL
dictionary_from_api-2.1.0.dist-info/top_level.txt
dictionary_from_api-2.1.0.dist-info/RECORD
