Metadata-Version: 2.1
Name: dictionary-from-api
Version: 2.1.0
Summary: UNKNOWN
Author: Osman Buğra Aydın
License: UNKNOWN
Platform: UNKNOWN
Requires-Python: >=3.8
Requires-Dist: requests (>=2.23.0)
